scraper/__init__.py
scraper/__main__.py
scraper/exceptions.py
scraper/package.json
scraper/scraper.py
scraper/wrapper.py
scraper/node_modules/.package-lock.json
scraper/node_modules/boolbase/README.md
scraper/node_modules/boolbase/index.js
scraper/node_modules/boolbase/package.json
scraper/node_modules/cheerio/Readme.md
scraper/node_modules/cheerio/package.json
scraper/node_modules/cheerio/lib/cheerio.js
scraper/node_modules/cheerio/lib/parse.js
scraper/node_modules/cheerio/lib/static.js
scraper/node_modules/cheerio/lib/utils.js
scraper/node_modules/cheerio/lib/api/attributes.js
scraper/node_modules/cheerio/lib/api/css.js
scraper/node_modules/cheerio/lib/api/forms.js
scraper/node_modules/cheerio/lib/api/manipulation.js
scraper/node_modules/cheerio/lib/api/traversing.js
scraper/node_modules/css-select/LICENSE
scraper/node_modules/css-select/README.md
scraper/node_modules/css-select/package.json
scraper/node_modules/css-select/lib/attributes.js
scraper/node_modules/css-select/lib/compile.js
scraper/node_modules/css-select/lib/general.js
scraper/node_modules/css-select/lib/sort.js
scraper/node_modules/css-what/LICENSE
scraper/node_modules/css-what/package.json
scraper/node_modules/css-what/readme.md
scraper/node_modules/d/.editorconfig
scraper/node_modules/d/CHANGELOG.md
scraper/node_modules/d/CHANGES
scraper/node_modules/d/LICENSE
scraper/node_modules/d/README.md
scraper/node_modules/d/auto-bind.js
scraper/node_modules/d/index.js
scraper/node_modules/d/lazy.js
scraper/node_modules/d/package.json
scraper/node_modules/d/.github/FUNDING.yml
scraper/node_modules/d/test/auto-bind.js
scraper/node_modules/d/test/index.js
scraper/node_modules/d/test/lazy.js
scraper/node_modules/debug/.coveralls.yml
scraper/node_modules/debug/.eslintrc
scraper/node_modules/debug/.npmignore
scraper/node_modules/debug/.travis.yml
scraper/node_modules/debug/CHANGELOG.md
scraper/node_modules/debug/LICENSE
scraper/node_modules/debug/Makefile
scraper/node_modules/debug/README.md
google_play_scraper_py-0.3.1.dist-info/LICENSE
google_play_scraper_py-0.3.1.dist-info/METADATA
google_play_scraper_py-0.3.1.dist-info/WHEEL
google_play_scraper_py-0.3.1.dist-info/entry_points.txt
google_play_scraper_py-0.3.1.dist-info/top_level.txt
google_play_scraper_py-0.3.1.dist-info/RECORD
