Metadata-Version: 2.1
Name: google-play-scraper-py
Version: 0.3.1
Summary: Scrape application data from the Google Play store.
Home-page: https://github.com/blues-lab/google-play-scraper-py
Author: Berkeley Lab for Usable and Experimental Security (BLUES)
Author-email: blues@berkeley.edu
License: MIT
Classifier: License :: OSI Approved :: MIT License
Classifier: Programming Language :: Python :: 3
Classifier: Programming Language :: Python :: 3.9
License-File: LICENSE
